setup.py
wwprocess/__init__.py
wwprocess.egg-info/PKG-INFO
wwprocess.egg-info/SOURCES.txt
wwprocess.egg-info/dependency_links.txt
wwprocess.egg-info/requires.txt
wwprocess.egg-info/top_level.txt
wwprocess/calculation/__init__.py
wwprocess/calculation/densify.py
wwprocess/calculation/dumpCalc.py
wwprocess/calculation/filt.py
wwprocess/calculation/process.py
wwprocess/calculation/rdt.py
wwprocess/calculation/specCalc.py
wwprocess/calculation/statCalc.py
wwprocess/dataset/__init__.py
wwprocess/dataset/loadTdms.py
wwprocess/dataset/mt.py
wwprocess/dataset/wt.py
wwprocess/plots/PlotSchema.py
wwprocess/plots/__init__.py