Metadata-Version: 1.2
Name: wwprocess
Version: 0.0.10
Summary: for processing windworks
Home-page: UNKNOWN
Author: jiang yuanji
Author-email: jiangyuanji@126.com
Maintainer: jiang yuanji
Maintainer-email: jiangyuanji@126.com
License: GNU License
Platform: all
Classifier: Development Status :: 4 - Beta
Classifier: Operating System :: OS Independent
Classifier: Intended Audience :: Developers
Classifier: License :: OSI Approved :: MIT License
Classifier: Programming Language :: Python
Classifier: Programming Language :: Python :: Implementation
Classifier: Programming Language :: Python :: 2
Classifier: Programming Language :: Python :: 2.7
Classifier: Programming Language :: Python :: 3
Classifier: Programming Language :: Python :: 3.4
Classifier: Programming Language :: Python :: 3.5
Classifier: Programming Language :: Python :: 3.6
Classifier: Programming Language :: Python :: 3.7
Classifier: Topic :: Software Development :: Libraries
